mylib/__init__.py
mylib/setup.py
mylib/datastructures/__init__.py
mylibKIv1/__init__.py
mylibKIv1/setup.py
mylibKIv1/datastructures/__init__.py
mylibKIv1/datastructures/linear/CDLL.py
mylibKIv1/datastructures/linear/CSLL.py
mylibKIv1/datastructures/linear/DLL.py
mylibKIv1/datastructures/linear/QueueLL.py
mylibKIv1/datastructures/linear/SLL.py
mylibKIv1/datastructures/linear/StackLL.py
mylibKIv1/datastructures/linear/__init__.py
mylibKIv1/datastructures/nodes/DNode.py
mylibKIv1/datastructures/nodes/SNode.py
mylibKIv1/datastructures/nodes/TNode.py
mylibKIv1/datastructures/nodes/__init__.py
mylibKIv1/datastructures/trees/__init__.py
mylibKIv1/datastructures/trees/avl.py
mylibKIv1/datastructures/trees/bst.py
mylibKIv1-1.1.dist-info/METADATA
mylibKIv1-1.1.dist-info/WHEEL
mylibKIv1-1.1.dist-info/top_level.txt
mylibKIv1-1.1.dist-info/RECORD
