Metadata-Version: 2.1
Name: mylibKIv1
Version: 1.1
Summary: final project for ensf 338
Home-page: UNKNOWN
Author: Isaac Hus and Kenzie Fjestad
Author-email: isaac.hus@ucalgary.ca, kenzie.fjestad@ucalgary.ca
License: UNKNOWN
Platform: UNKNOWN
